[
  {
    "id": "2026-07-23-session-recap",
    "filename": "2026-07-23-session-recap.md",
    "title": "Daily Recap: High-Precision Session (+69.85% Win Rate, +$92.80 Net Profit)",
    "date": "2026-07-23",
    "category": "Daily Recap",
    "tickers": ["$POCKETOPTION", "$EURUSD", "$AUDCHF", "$AUDUSD"],
    "outcome": "Win",
    "readTime": "4 min",
    "excerpt": "Syncing latest Pocket Option trades from Google Sheet: 137 trades executed, 95 Wins / 41 Losses, generating +$92.80 in net profit."
  },
  {
    "id": "2026-07-22-pocket-option-critical-analysis",
    "filename": "2026-07-22-pocket-option-critical-analysis.md",
    "title": "Critical Deep Dive: Quantitative Analysis of 2,836 Pocket Option Executions",
    "date": "2026-07-22",
    "category": "Post-Mortem",
    "tickers": ["$POCKETOPTION", "$AUDCHF", "$CADCHF", "$CADJPY", "$EURUSD"],
    "outcome": "Loss",
    "readTime": "8 min",
    "excerpt": "A comprehensive data analysis of 2,836 binary trades uncovering hidden statistical edges, money-draining assets, and the 5-minute expiry breakthrough."
  },
  {
    "id": "2026-07-21-pocket-option-funding",
    "filename": "2026-07-21-pocket-option-funding.md",
    "title": "Pocket Option Capital Flow: Scaling with $500 Deposit & System Discipline",
    "date": "2026-07-21",
    "category": "Pocket Option Log",
    "tickers": ["$POCKETOPTION", "$EURUSD"],
    "outcome": "Win",
    "readTime": "4 min",
    "excerpt": "Logging a major capital milestone on Pocket Option with a $500 bank transfer deposit and analyzing my capital flow metrics."
  },
  {
    "id": "2026-07-20-pocket-option-rules",
    "filename": "2026-07-20-pocket-option-rules.md",
    "title": "Day 1: Immutable Binary Options Rules & System Hygiene",
    "date": "2026-07-20",
    "category": "Strategy & Rules",
    "tickers": ["$POCKETOPTION", "$EURUSD", "$AUDCHF"],
    "outcome": "N/A",
    "readTime": "4 min",
    "excerpt": "Setting up the core framework for binary option stake management, max daily loss limits, and execution discipline."
  }
]
